<?xml version="1.0" encoding="UTF-8"?>
<krpano version="1.18"
        onstart="startup"
        logkey="false"
        bgcolor="#ffffff"
        projectfloorplanurl=""
        projecttitleid="project_title"
        projectdescriptionid="project_description">


  <security cors="">
  </security>

  <krpano tour_firststartactiondone="false" />
  <events name="startbehavioursevents" onxmlcomplete="startbehavioursxmlcompleteaction();" keep="true"/>

  <!-- generated by Panotour Pro V2.3.1 64bits : 04-02-2015 17-47-41 -->
  <!-- Plugins and Spot Styles -->
  <include url="%FIRSTXML%/sna_skin.xml"/>
  <!-- Core actions -->
  <include url="%FIRSTXML%/sna_core.xml"/>
  <!-- Tour Messages -->
  <include url="%FIRSTXML%/sna_messages_en.xml"/>

  <action name="startup">

    if (skipintro !== null, skipintroaction(); );
    if (s !== null, if (startscene === null, set(startscene, get(s));); );
    if (startscene === null,
      set(startscene, pano230);
    );
    mainloadscene(get(startscene));
    if (h !== null,
      if (v !== null,
        if (f !== null,
          lookat(get(h), get(v), get(f));
         ,
          lookat(get(h), get(v));
        );
      );
    );
  </action>



  <!-- 4 Groups -->

  <!-- Group Groupe 231 : 1 panoramas -->


<!-- **** @PanoName="Appareillage" @PanoFile="/Users/Image/Documents/Visites Virtuelles/Retouches/SNA/appareillage.jpg" **** -->
<!-- **** Width="8042px" Height="4021px" **** -->
<scene name="pano230"
       heading="0"
       thumburl="%FIRSTXML%/appareillage_230/thumbnail.jpg"
       backgroundsound=""
       backgroundsoundloops="0"
       titleid="pano230_title"
       descriptionid=""
       multires="false"
       planar="false"
       full360="true"
       seen="false">


    <autorotate horizon="-12.413793" tofov="90.000000" waittime="5" speed="5"/>

    <panoview h="53.645320" v="-12.413793" fov="90.000000" hmin="-180" hmax="180" vmin="-90" vmax="59.215291750503" fovmax="90" />

    <view fisheye="0"
          limitview="range"
          hlookatmin="-180"
          hlookatmax="180"
          vlookatmin="-90"
          vlookatmax="59.215291750503"
          maxpixelzoom="1.0"
          fovtype="VFOV"
          fovmax="90"
          fov="90.000000"
          hlookat="53.645320"
          vlookat="-12.413793"/>

    <preview url="%FIRSTXML%/appareillage_230/preview.jpg" type="CUBESTRIP" striporder="FRBLUD"/>

    <image type="CUBE" devices="desktop|html5">
      <front url="appareillage_230/html5/0.jpg"/>
      <right url="appareillage_230/html5/1.jpg"/>
      <back  url="appareillage_230/html5/2.jpg"/>
      <left  url="appareillage_230/html5/3.jpg"/>
      <up    url="appareillage_230/html5/4.jpg"/>
      <down  url="appareillage_230/html5/5.jpg"/>
    </image>

    <image type="CUBE" devices="tablet">
      <front url="appareillage_230/tablet/0.jpg"/>
      <right url="appareillage_230/tablet/1.jpg"/>
      <back  url="appareillage_230/tablet/2.jpg"/>
      <left  url="appareillage_230/tablet/3.jpg"/>
      <up    url="appareillage_230/tablet/4.jpg"/>
      <down  url="appareillage_230/tablet/5.jpg"/>
    </image>
    <image type="CUBE" devices="mobile">
      <front url="appareillage_230/mobile/0.jpg"/>
      <right url="appareillage_230/mobile/1.jpg"/>
      <back  url="appareillage_230/mobile/2.jpg"/>
      <left  url="appareillage_230/mobile/3.jpg"/>
      <up    url="appareillage_230/mobile/4.jpg"/>
      <down  url="appareillage_230/mobile/5.jpg"/>
    </image>




  <action name="setzorder2onstandardspots">
    if (device.html5,
      ifnot (device.desktop,


      );
    );
  </action>


</scene>


  <!-- Group Groupe 246 : 1 panoramas -->


<!-- **** @PanoName="Plage avant " @PanoFile="/Users/Image/Documents/Visites Virtuelles/Retouches/SNA/plage_avant_3.jpg" **** -->
<!-- **** Width="8050px" Height="4025px" **** -->
<scene name="pano246"
       heading="0"
       thumburl="%FIRSTXML%/plage_avant_246/thumbnail.jpg"
       backgroundsound=""
       backgroundsoundloops="0"
       titleid="pano246_title"
       descriptionid=""
       multires="false"
       planar="false"
       full360="true"
       seen="false">


    <autorotate horizon="2.686567" tofov="90.000000" waittime="5" speed="5"/>

    <panoview h="-174.679803" v="2.686567" fov="90.000000" hmin="-180" hmax="180" vmin="-90" vmax="47.6865671641791" fovmax="90" />

    <view fisheye="0"
          limitview="range"
          hlookatmin="-180"
          hlookatmax="180"
          vlookatmin="-90"
          vlookatmax="47.6865671641791"
          maxpixelzoom="1.0"
          fovtype="VFOV"
          fovmax="90"
          fov="90.000000"
          hlookat="-174.679803"
          vlookat="2.686567"/>

    <preview url="%FIRSTXML%/plage_avant_246/preview.jpg" type="CUBESTRIP" striporder="FRBLUD"/>

    <image type="CUBE" devices="desktop|html5">
      <front url="plage_avant_246/html5/0.jpg"/>
      <right url="plage_avant_246/html5/1.jpg"/>
      <back  url="plage_avant_246/html5/2.jpg"/>
      <left  url="plage_avant_246/html5/3.jpg"/>
      <up    url="plage_avant_246/html5/4.jpg"/>
      <down  url="plage_avant_246/html5/5.jpg"/>
    </image>

    <image type="CUBE" devices="tablet">
      <front url="plage_avant_246/tablet/0.jpg"/>
      <right url="plage_avant_246/tablet/1.jpg"/>
      <back  url="plage_avant_246/tablet/2.jpg"/>
      <left  url="plage_avant_246/tablet/3.jpg"/>
      <up    url="plage_avant_246/tablet/4.jpg"/>
      <down  url="plage_avant_246/tablet/5.jpg"/>
    </image>
    <image type="CUBE" devices="mobile">
      <front url="plage_avant_246/mobile/0.jpg"/>
      <right url="plage_avant_246/mobile/1.jpg"/>
      <back  url="plage_avant_246/mobile/2.jpg"/>
      <left  url="plage_avant_246/mobile/3.jpg"/>
      <up    url="plage_avant_246/mobile/4.jpg"/>
      <down  url="plage_avant_246/mobile/5.jpg"/>
    </image>




  <action name="setzorder2onstandardspots">
    if (device.html5,
      ifnot (device.desktop,


      );
    );
  </action>


</scene>


  <!-- Group Groupe 235 : 1 panoramas -->


<!-- **** @PanoName="Central Opérations" @PanoFile="/Users/Image/Documents/Visites Virtuelles/Retouches/SNA/periscope.jpg" **** -->
<!-- **** Width="8086px" Height="4043px" **** -->
<scene name="pano234"
       heading="0"
       thumburl="%FIRSTXML%/central_operations_234/thumbnail.jpg"
       backgroundsound=""
       backgroundsoundloops="0"
       titleid="pano234_title"
       descriptionid=""
       multires="false"
       planar="false"
       full360="true"
       seen="false">


    <autorotate horizon="-29.704433" tofov="90.000000" waittime="5" speed="5"/>

    <panoview h="7.093596" v="-29.704433" fov="90.000000" hmin="-180" hmax="180" vmin="-90" vmax="58.8531187122736" fovmax="90" />

    <view fisheye="0"
          limitview="range"
          hlookatmin="-180"
          hlookatmax="180"
          vlookatmin="-90"
          vlookatmax="58.8531187122736"
          maxpixelzoom="1.0"
          fovtype="VFOV"
          fovmax="90"
          fov="90.000000"
          hlookat="7.093596"
          vlookat="-29.704433"/>

    <preview url="%FIRSTXML%/central_operations_234/preview.jpg" type="CUBESTRIP" striporder="FRBLUD"/>

    <image type="CUBE" devices="desktop|html5">
      <front url="central_operations_234/html5/0.jpg"/>
      <right url="central_operations_234/html5/1.jpg"/>
      <back  url="central_operations_234/html5/2.jpg"/>
      <left  url="central_operations_234/html5/3.jpg"/>
      <up    url="central_operations_234/html5/4.jpg"/>
      <down  url="central_operations_234/html5/5.jpg"/>
    </image>

    <image type="CUBE" devices="tablet">
      <front url="central_operations_234/tablet/0.jpg"/>
      <right url="central_operations_234/tablet/1.jpg"/>
      <back  url="central_operations_234/tablet/2.jpg"/>
      <left  url="central_operations_234/tablet/3.jpg"/>
      <up    url="central_operations_234/tablet/4.jpg"/>
      <down  url="central_operations_234/tablet/5.jpg"/>
    </image>
    <image type="CUBE" devices="mobile">
      <front url="central_operations_234/mobile/0.jpg"/>
      <right url="central_operations_234/mobile/1.jpg"/>
      <back  url="central_operations_234/mobile/2.jpg"/>
      <left  url="central_operations_234/mobile/3.jpg"/>
      <up    url="central_operations_234/mobile/4.jpg"/>
      <down  url="central_operations_234/mobile/5.jpg"/>
    </image>




  <action name="setzorder2onstandardspots">
    if (device.html5,
      ifnot (device.desktop,


      );
    );
  </action>


</scene>


  <!-- Group Groupe 237 : 1 panoramas -->


<!-- **** @PanoName="Cafétériat" @PanoFile="/Users/Image/Documents/Visites Virtuelles/Retouches/SNA/cafeteriat.jpg" **** -->
<!-- **** Width="8087px" Height="3466px" **** -->
<scene name="pano236"
       heading="0"
       thumburl="%FIRSTXML%/cafeteriat_236/thumbnail.jpg"
       backgroundsound=""
       backgroundsoundloops="0"
       titleid="pano236_title"
       descriptionid=""
       multires="false"
       planar="false"
       full360="false"
       seen="false">


    <autorotate horizon="18.620690" tofov="90.000000" waittime="5" speed="5"/>

    <panoview h="-23.940887" v="18.620690" fov="90.000000" hmin="-180" hmax="180" vmin="-61.9787323943662" vmax="64.81" fovmax="90" />

    <view fisheye="0"
          limitview="range"
          hlookatmin="-180"
          hlookatmax="180"
          vlookatmin="-61.9787323943662"
          vlookatmax="64.81"
          maxpixelzoom="1.0"
          fovtype="VFOV"
          fovmax="90"
          fov="90.000000"
          hlookat="-23.940887"
          vlookat="18.620690"/>

    <preview url="%FIRSTXML%/cafeteriat_236/preview.jpg" type="CUBESTRIP" striporder="FRBLUD"/>



  <image type="CUBE" devices="desktop">
    <front url="cafeteriat_236/html5/0.jpg"/>
    <right url="cafeteriat_236/html5/1.jpg"/>
    <back  url="cafeteriat_236/html5/2.jpg"/>
    <left  url="cafeteriat_236/html5/3.jpg"/>
    <up    url="cafeteriat_236/html5/4.jpg"/>
    <down  url="cafeteriat_236/html5/5.jpg"/>
  </image>

      <image type="CUBE" devices="tablet">
        <front url="cafeteriat_236/tablet/0.jpg"/>
        <right url="cafeteriat_236/tablet/1.jpg"/>
        <back  url="cafeteriat_236/tablet/2.jpg"/>
        <left  url="cafeteriat_236/tablet/3.jpg"/>
        <up    url="cafeteriat_236/tablet/4.jpg"/>
        <down  url="cafeteriat_236/tablet/5.jpg"/>
      </image>
      <image type="CUBE" devices="mobile">
        <front url="cafeteriat_236/mobile/0.jpg"/>
        <right url="cafeteriat_236/mobile/1.jpg"/>
        <back  url="cafeteriat_236/mobile/2.jpg"/>
        <left  url="cafeteriat_236/mobile/3.jpg"/>
        <up    url="cafeteriat_236/mobile/4.jpg"/>
        <down  url="cafeteriat_236/mobile/5.jpg"/>
      </image>


  <action name="setzorder2onstandardspots">
    if (device.html5,
      ifnot (device.desktop,


      );
    );
  </action>


</scene>




  <!-- Awake HTML5 plugins -->
  <events name="eventKrpanoLoadedEvts" onxmlcomplete="eventKrpanoLoadedAction();" keep="true" />
  <action name="eventKrpanoLoadedAction">

    set(events[eventKrpanoLoadedEvts].name, null);
    js(eventKrpanoLoaded());
  </action>

</krpano>
